{
  "name": "catppuccin-latte",
  "editor": {
    "bg": [239, 241, 245],
    "fg": [76, 79, 105],
    "cursor": [220, 138, 120],
    "inactive_cursor": [140, 143, 161],
    "selection_bg": [188, 192, 204],
    "current_line_bg": [204, 208, 218],
    "line_number_fg": [140, 143, 161],
    "line_number_bg": [239, 241, 245],
    "diff_add_bg": [210, 235, 208],
    "diff_remove_bg": [245, 210, 218],
    "diff_modify_bg": [220, 225, 240]
  },
  "ui": {
    "tab_active_fg": [76, 79, 105],
    "tab_active_bg": [204, 208, 218],
    "tab_inactive_fg": [108, 111, 133],
    "tab_inactive_bg": [230, 233, 239],
    "tab_separator_bg": [204, 208, 218],
    "tab_close_hover_fg": [210, 15, 57],
    "tab_hover_bg": [204, 208, 218],
    "menu_bg": [230, 233, 239],
    "menu_fg": [76, 79, 105],
    "menu_active_bg": [204, 208, 218],
    "menu_active_fg": [76, 79, 105],
    "menu_dropdown_bg": [230, 233, 239],
    "menu_dropdown_fg": [76, 79, 105],
    "menu_highlight_bg": [30, 102, 245],
    "menu_highlight_fg": [239, 241, 245],
    "menu_border_fg": [172, 176, 190],
    "menu_separator_fg": [188, 192, 204],
    "menu_hover_bg": [204, 208, 218],
    "menu_hover_fg": [76, 79, 105],
    "menu_disabled_fg": [156, 160, 176],
    "menu_disabled_bg": [230, 233, 239],
    "status_bar_fg": [76, 79, 105],
    "status_bar_bg": [230, 233, 239],
    "prompt_fg": [76, 79, 105],
    "prompt_bg": [220, 224, 232],
    "prompt_selection_fg": [76, 79, 105],
    "prompt_selection_bg": [188, 192, 204],
    "popup_border_fg": [172, 176, 190],
    "popup_bg": [230, 233, 239],
    "popup_selection_bg": [204, 208, 218],
    "popup_text_fg": [76, 79, 105],
    "suggestion_bg": [230, 233, 239],
    "suggestion_selected_bg": [204, 208, 218],
    "help_bg": [220, 224, 232],
    "help_fg": [76, 79, 105],
    "help_key_fg": [30, 102, 245],
    "help_separator_fg": [188, 192, 204],
    "help_indicator_fg": [210, 15, 57],
    "help_indicator_bg": [220, 224, 232],
    "inline_code_bg": [204, 208, 218],
    "split_separator_fg": [172, 176, 190],
    "split_separator_hover_fg": [30, 102, 245],
    "scrollbar_track_fg": [204, 208, 218],
    "scrollbar_thumb_fg": [172, 176, 190],
    "scrollbar_track_hover_fg": [188, 192, 204],
    "scrollbar_thumb_hover_fg": [140, 143, 161],
    "compose_margin_bg": [220, 224, 232],
    "semantic_highlight_bg": [204, 208, 218],
    "terminal_bg": "Default",
    "terminal_fg": "Default",
    "status_warning_indicator_bg": [223, 142, 29],
    "status_warning_indicator_fg": [239, 241, 245],
    "status_error_indicator_bg": [210, 15, 57],
    "status_error_indicator_fg": [239, 241, 245],
    "status_warning_indicator_hover_bg": [254, 100, 11],
    "status_warning_indicator_hover_fg": [239, 241, 245],
    "status_error_indicator_hover_bg": [230, 69, 83],
    "status_error_indicator_hover_fg": [239, 241, 245],
    "tab_drop_zone_bg": [30, 102, 245],
    "tab_drop_zone_border": [114, 135, 253],
    "settings_selected_bg": [204, 208, 218],
    "settings_selected_fg": [76, 79, 105]
  },
  "search": {
    "match_bg": [223, 142, 29],
    "match_fg": [239, 241, 245]
  },
  "diagnostic": {
    "error_fg": [210, 15, 57],
    "error_bg": [245, 220, 225],
    "warning_fg": [223, 142, 29],
    "warning_bg": [245, 235, 210],
    "info_fg": [4, 165, 229],
    "info_bg": [215, 240, 248],
    "hint_fg": [124, 127, 147],
    "hint_bg": [225, 228, 238]
  },
  "syntax": {
    "keyword": [136, 57, 239],
    "string": [64, 160, 43],
    "comment": [124, 127, 147],
    "function": [30, 102, 245],
    "type": [223, 142, 29],
    "variable": [76, 79, 105],
    "constant": [254, 100, 11],
    "operator": [23, 146, 153]
  }
}
